meafs-6.2.1.dist-info/licenses/LICENSE.txt
meafs_code/__init__.py
meafs_code/__main__.py
meafs_code/convert.sh
meafs_code/desktop_entry.py
meafs_code/fitsettings.ui
meafs_code/fitsettings_qt.py
meafs_code/gui.py
meafs_code/gui_qt.py
meafs_code/meafs.ui
meafs_code/normalize.ui
meafs_code/normalize_qt.py
meafs_code/settings.csv
meafs_code/images/Meafs_Gui.png
meafs_code/images/Meafs_Icon.ico
meafs_code/images/Meafs_Icon.png
meafs_code/images/Meafs_Logo.png
meafs_code/images/github-mark-white.svg
meafs_code/images/github-mark.svg
meafs_code/images/logo-dark-rtd.svg
meafs_code/images/logo-light-rtd.svg
meafs_code/scripts/__init__.py
meafs_code/scripts/abundance_fit.py
meafs_code/scripts/abundance_plot.py
meafs_code/scripts/bisec_interpol.c
meafs_code/scripts/comp.sh
meafs_code/scripts/fit_functions.py
meafs_code/scripts/turbospec_functions.py
meafs_code/scripts/unify_plots.py
meafs_code/scripts/voigt_functions.py
meafs-6.2.1.dist-info/METADATA
meafs-6.2.1.dist-info/WHEEL
meafs-6.2.1.dist-info/entry_points.txt
meafs-6.2.1.dist-info/top_level.txt
meafs-6.2.1.dist-info/RECORD
