Metadata-Version: 2.4
Name: meafs
Version: 6.2.1
Summary: Multiple Element Abundance Fit Software
Author: Matheus J. Castro
Project-URL: homepage, https://meafs.readthedocs.io/
Project-URL: repository, https://github.com/MatheusJCastro/meafs
Classifier: Programming Language :: Python :: 3
Classifier: License :: OSI Approved :: MIT License
Classifier: Operating System :: OS Independent
Requires-Python: >=3.11
License-File: LICENSE.txt
Requires-Dist: astropy>=5.3.1
Requires-Dist: specutils>=1.17.0
Requires-Dist: scipy>=1.11.1
Requires-Dist: matplotlib>=3.9.2
Requires-Dist: pandas>=2.2.0
Requires-Dist: numpy>=1.24.4
Requires-Dist: desktop_file==1.3
Requires-Dist: pathlib>=1.0.1
Requires-Dist: PyQt6>=6.7.1
Requires-Dist: dill>=0.3.7
Requires-Dist: qtconsole>=5.4.3
Dynamic: license-file
